spy4cast/__init__.py
spy4cast/_functions.py
spy4cast/errors.py
spy4cast/meteo.py
spy4cast/plotters.py
spy4cast/read_data.py
spy4cast/spy4caster.py
spy4cast/stypes.py
spy4cast-0.0.14.dist-info/LICENSE
spy4cast-0.0.14.dist-info/METADATA
spy4cast-0.0.14.dist-info/WHEEL
spy4cast-0.0.14.dist-info/top_level.txt
spy4cast-0.0.14.dist-info/RECORD
