Metadata-Version: 2.1
Name: spy4cast
Version: 0.0.14
Summary: Python API for applying methodologies to .nc Datasets
Home-page: https://github.com/pabloduran016/Spy4Cast
Author: Pablo Duran
Author-email: pdrm56@gmail.com
License: UNKNOWN
Project-URL: Repo, https://github.com/pabloduran016/Spy4Cast
Project-URL: Documentation, https://spy4cast-docs.netlify.app
Platform: UNKNOWN
Classifier: Programming Language :: Python :: 3
Classifier: License :: OSI Approved :: GNU Lesser General Public License v2 (LGPLv2)
Classifier: Operating System :: OS Independent
Requires-Python: >=3.6
License-File: LICENSE
Requires-Dist: numpy
Requires-Dist: matplotlib
Requires-Dist: xarray
Requires-Dist: dask
Requires-Dist: pandas
Requires-Dist: netcdf4
